{
	"configurations" : 
	[
		{
			"directories" : 
			[
				{
					"build" : ".",
					"hasInstallRule" : true,
					"jsonFile" : "directory-.-14d177f35ad4f72e089f.json",
					"minimumCMakeVersion" : 
					{
						"string" : "3.12"
					},
					"projectIndex" : 0,
					"source" : ".",
					"targetIndexes" : 
					[
						0,
						1
					]
				}
			],
			"name" : "",
			"projects" : 
			[
				{
					"directoryIndexes" : 
					[
						0
					],
					"name" : "isaacsim",
					"targetIndexes" : 
					[
						0,
						1
					]
				}
			],
			"targets" : 
			[
				{
					"directoryIndex" : 0,
					"id" : "isaacsim_uninstall::@6890427a1f51a3e7e1df",
					"jsonFile" : "target-isaacsim_uninstall-3063550083136eccc37a.json",
					"name" : "isaacsim_uninstall",
					"projectIndex" : 0
				},
				{
					"directoryIndex" : 0,
					"id" : "uninstall::@6890427a1f51a3e7e1df",
					"jsonFile" : "target-uninstall-976389a5608123492d20.json",
					"name" : "uninstall",
					"projectIndex" : 0
				}
			]
		}
	],
	"kind" : "codemodel",
	"paths" : 
	{
		"build" : "/home/home/dcp_ws/build/isaacsim",
		"source" : "/home/home/dcp_ws/src/fairino/isaacsim"
	},
	"version" : 
	{
		"major" : 2,
		"minor" : 3
	}
}
